toga_web/__init__.py
toga_web/app.py
toga_web/command.py
toga_web/dialogs.py
toga_web/factory.py
toga_web/fonts.py
toga_web/icons.py
toga_web/libs.py
toga_web/paths.py
toga_web/screens.py
toga_web/statusicons.py
toga_web/window.py
toga_web/resources/toga.png
toga_web/static/toga.css
toga_web/widgets/__init__.py
toga_web/widgets/activityindicator.py
toga_web/widgets/base.py
toga_web/widgets/box.py
toga_web/widgets/button.py
toga_web/widgets/dateinput.py
toga_web/widgets/divider.py
toga_web/widgets/label.py
toga_web/widgets/passwordinput.py
toga_web/widgets/progressbar.py
toga_web/widgets/scrollcontainer.py
toga_web/widgets/selection.py
toga_web/widgets/slider.py
toga_web/widgets/switch.py
toga_web/widgets/textinput.py
toga_web/widgets/timeinput.py
toga_web-0.5.2.dist-info/licenses/LICENSE
toga_web-0.5.2.dist-info/METADATA
toga_web-0.5.2.dist-info/WHEEL
toga_web-0.5.2.dist-info/entry_points.txt
toga_web-0.5.2.dist-info/top_level.txt
toga_web-0.5.2.dist-info/RECORD
