Metadata-Version: 2.4
Name: toga-web
Version: 0.5.2
Summary: A Web backend for the Toga widget toolkit.
Author-email: Russell Keith-Magee <russell@keith-magee.com>
Maintainer-email: BeeWare Team <team@beeware.org>
License-Expression: BSD-3-Clause
Project-URL: Homepage, https://beeware.org/project/projects/libraries/toga/
Project-URL: Funding, https://beeware.org/contributing/membership/
Project-URL: Documentation, https://toga.readthedocs.io/
Project-URL: Tracker, https://github.com/beeware/toga/issues
Project-URL: Source, https://github.com/beeware/toga
Project-URL: Changelog, https://toga.readthedocs.io/en/stable/background/project/releases.html
Keywords: gui,widget,cross-platform,toga,web,pyscript,pyodide,wasm
Classifier: Development Status :: 4 - Beta
Classifier: Intended Audience :: Developers
Classifier: Operating System :: OS Independent
Classifier: Programming Language :: Python :: 3
Classifier: Programming Language :: Python :: 3.9
Classifier: Programming Language :: Python :: 3.10
Classifier: Programming Language :: Python :: 3.11
Classifier: Programming Language :: Python :: 3.12
Classifier: Programming Language :: Python :: 3.13
Classifier: Programming Language :: Python :: 3 :: Only
Classifier: Topic :: Software Development
Classifier: Topic :: Software Development :: User Interfaces
Classifier: Topic :: Software Development :: Widget Sets
Requires-Python: >=3.9
License-File: LICENSE
Requires-Dist: toga-core==0.5.2
Dynamic: license-file
Dynamic: requires-dist
